quantatrisk_tradetool/__init__.py
quantatrisk_tradetool/__main__.py
quantatrisk_tradetool/analitics/__init__.py
quantatrisk_tradetool/calc/__init__.py
quantatrisk_tradetool/calc/compute.py
quantatrisk_tradetool/data/__init__.py
quantatrisk_tradetool/data/load.py
quantatrisk_tradetool/stream/__init__.py
quantatrisk_tradetool/stream/ccrypto.py
quantatrisk_tradetool-0.0.2.dist-info/AUTHORS.rst
quantatrisk_tradetool-0.0.2.dist-info/LICENSE
quantatrisk_tradetool-0.0.2.dist-info/METADATA
quantatrisk_tradetool-0.0.2.dist-info/WHEEL
quantatrisk_tradetool-0.0.2.dist-info/entry_points.txt
quantatrisk_tradetool-0.0.2.dist-info/top_level.txt
quantatrisk_tradetool-0.0.2.dist-info/RECORD
