Metadata-Version: 2.1
Name: quantatrisk-tradetool
Version: 0.0.2
Summary: Internal tooling
Home-page: https://quantatrisk_tradetool/pablomasior/python-quantatrisk_tradetool
Author: pawel masior
Author-email: pablo.masior@gmail.com
License: BSD-2-Clause
Project-URL: Documentation, https://python-quantatrisk_tradetool.readthedocs.io/
Project-URL: Changelog, https://python-quantatrisk_tradetool.readthedocs.io/en/latest/changelog.html
Project-URL: Issue Tracker, https://quantatrisk_tradetool/pablomasior/python-quantatrisk_tradetool/issues
Platform: UNKNOWN
Classifier: Development Status :: 5 - Production/Stable
Classifier: Intended Audience :: Developers
Classifier: License :: OSI Approved :: BSD License
Classifier: Operating System :: Unix
Classifier: Operating System :: POSIX
Classifier: Operating System :: Microsoft :: Windows
Classifier: Programming Language :: Python
Classifier: Programming Language :: Python :: 3
Classifier: Programming Language :: Python :: 3 :: Only
Classifier: Programming Language :: Python :: 3.6
Classifier: Programming Language :: Python :: 3.7
Classifier: Programming Language :: Python :: 3.8
Classifier: Programming Language :: Python :: 3.9
Classifier: Programming Language :: Python :: 3.10
Classifier: Programming Language :: Python :: Implementation :: CPython
Classifier: Programming Language :: Python :: Implementation :: PyPy
Classifier: Topic :: Utilities
Requires-Python: >=3.6
License-File: LICENSE
License-File: AUTHORS.rst
